rtl/pe.sv
// Processing Element
timeunit 1ns; timeprecision 1ps;

module pe #(
    parameter DATA_WIDTH = 8,
    parameter ACCUM_WIDTH = 32
)(
    input logic i_clk,
    input logic rst_n,
    input logic signed [DATA_WIDTH-1:0] i_data,
    input logic signed [DATA_WIDTH-1:0] i_weight,
    input logic signed [ACCUM_WIDTH-1:0] i_psum,
    
    output logic signed [DATA_WIDTH-1:0] o_data,
    output logic signed [DATA_WIDTH-1:0] o_weight,
    output logic signed [ACCUM_WIDTH-1:0] o_psum
);
    logic signed [DATA_WIDTH-1:0] data_r, weight_r;
    logic signed [ACCUM_WIDTH-1:0] psum_r;
    logic signed [2*ACCUM_WIDTH-1:0] mult_r;
    logic signed [ACCUM_WIDTH-1:0] mac_r;

    always_ff @(posedge i_clk) begin
        if (!rst_n) begin
            data_r   <= '0;
            weight_r <= '0;
            psum_r   <= '0;
            mult_r   <= '0;
            mac_r    <= '0;
            o_psum   <= '0;
            o_data   <= '0;
            o_weight <= '0;
        end else begin
            data_r <= i_data;
            weight_r <= i_weight;
            psum_r <= i_psum;
            mult_r <= data_r * weight_r; // Mult stage
            mac_r <= psum_r + mult_r;   // Add stage
            o_psum <= mac_r;
            o_data <= data_r;
            o_weight <= weight_r;
        end
    end

endmodule

tb/tb_pe.sv
// tb_pe.sv - Testbench for pe.sv
timeunit 1ns; timeprecision 1ps;

module tb_pe;
    parameter DATA_WIDTH  = 8;
    parameter ACCUM_WIDTH = 32;

    localparam NUM_TESTS = 112; // Default: 12 corners + 100 random = 112
    localparam PIPELINE_DEPTH = 3;

    logic clk, rst_n;
    logic signed [DATA_WIDTH-1:0]  data_in,   data_out;
    logic signed [DATA_WIDTH-1:0]  weight_in, weight_out;
    logic signed [ACCUM_WIDTH-1:0] psum_in,   psum_out;

    pe #(
        .DATA_WIDTH (DATA_WIDTH),
        .ACCUM_WIDTH(ACCUM_WIDTH)
    ) dut (
        .i_clk    (clk),
        .rst_n    (rst_n),
        .i_data   (data_in),
        .i_weight (weight_in),
        .i_psum   (psum_in),
        .o_data   (data_out),
        .o_weight (weight_out),
        .o_psum   (psum_out)
    );

    initial clk = 0;
    always #5 clk = ~clk;  // 100 MHz

    int pass_count = 0;
    int fail_count = 0;

    task automatic reset_dut;
        rst_n   = 0;
        data_in = '0;  weight_in = '0;  psum_in = '0;
        repeat(2) @(posedge clk);
        rst_n = 1;
        @(posedge clk); #1;
        $display("[RESET] DUT reset complete");
    endtask

    task automatic test_mid_reset;
        $display("[TEST] Mid-simulation reset...");
        data_in = 8'd5;  weight_in = 8'd3;  psum_in = 32'd999;
        repeat(2) @(posedge clk);
        rst_n = 0; @(posedge clk); #1;

        if (data_out !== '0 || weight_out !== '0 || psum_out !== '0) begin
            $error("[FAIL] Mid-reset: outputs not cleared  data_out=%0h weight_out=%0h psum_out=%0h",
                   data_out, weight_out, psum_out);
            fail_count++;
        end else begin
            $display("[PASS] Mid-reset: outputs cleared");
            pass_count++;
        end

        if (dut.data_r !== '0 || dut.mult_r !== '0 || dut.mac_r !== '0) begin
            $error("[FAIL] Mid-reset: internal regs not cleared  data_r=%0h mult_r=%0h mac_r=%0h",
                   dut.data_r, dut.mult_r, dut.mac_r);
            fail_count++;
        end else begin
            $display("[PASS] Mid-reset: internal regs cleared");
            pass_count++;
        end
        rst_n = 1;
        @(posedge clk); #1;
    endtask

    logic [DATA_WIDTH-1:0]    raw_data   [0:NUM_TESTS-1];
    logic [DATA_WIDTH-1:0]    raw_weight [0:NUM_TESTS-1];
    logic [ACCUM_WIDTH-1:0]   raw_psum   [0:NUM_TESTS-1];
    logic [2*DATA_WIDTH-1:0]  raw_mult   [0:NUM_TESTS-1];  // 16-bit for 8b inputs
    logic [ACCUM_WIDTH-1:0]   raw_mac    [0:NUM_TESTS-1];

    logic signed [DATA_WIDTH-1:0]   tv_data   [0:NUM_TESTS-1];
    logic signed [DATA_WIDTH-1:0]   tv_weight [0:NUM_TESTS-1];
    logic signed [ACCUM_WIDTH-1:0]  tv_psum   [0:NUM_TESTS-1];
    logic signed [2*DATA_WIDTH-1:0] gold_mult [0:NUM_TESTS-1];
    logic signed [ACCUM_WIDTH-1:0]  gold_mac  [0:NUM_TESTS-1];

    initial begin
        $dumpfile("tb_pe.vcd");
        $dumpvars(0, tb_pe);

        $readmemh("sim/pe/tv_data.hex",   raw_data);
        $readmemh("sim/pe/tv_weight.hex", raw_weight);
        $readmemh("sim/pe/tv_psum.hex",   raw_psum);
        $readmemh("sim/pe/gold_mult.hex", raw_mult);
        $readmemh("sim/pe/gold_mac.hex",  raw_mac);

        // Cast to signed for downstream comparisons
        for (int i = 0; i < NUM_TESTS; i++) begin
            tv_data[i]   = signed'(raw_data[i]);
            tv_weight[i] = signed'(raw_weight[i]);
            tv_psum[i]   = signed'(raw_psum[i]);
            gold_mult[i] = signed'(raw_mult[i]);
            gold_mac[i]  = signed'(raw_mac[i]);
        end
        $display("[INIT] Loaded %0d test vectors", NUM_TESTS);

        reset_dut();

        for (int i = 0; i < NUM_TESTS; i++) begin
            data_in   = tv_data[i];
            weight_in = tv_weight[i];
            psum_in   = tv_psum[i];

            repeat(PIPELINE_DEPTH) @(posedge clk); #1;

            // Multiply check
            if (dut.mult_r[2*DATA_WIDTH-1:0] !== gold_mult[i]) begin
                $error("[FAIL] vec[%0d] MULT: got=%0h  exp=%0h  (%0d * %0d)",
                       i, dut.mult_r[2*DATA_WIDTH-1:0], gold_mult[i],
                       tv_data[i], tv_weight[i]);
                fail_count++;
            end else begin
                pass_count++;
            end

            // MAC check
            if (dut.mac_r !== gold_mac[i]) begin
                $error("[FAIL] vec[%0d] MAC:  got=%0h  exp=%0h  (psum=%0d mult=%0d)",
                       i, dut.mac_r, gold_mac[i], tv_psum[i], gold_mult[i]);
                fail_count++;
            end else begin
                pass_count++;
            end
        end

        test_mid_reset();

        // Summary
        $display("Summary");
        $display("Pass count: %0d", pass_count);
        $display("Fail count: %0d", fail_count);
        $display("Total count: %0d", pass_count + fail_count);
        
        if (fail_count == 0)
            $display("ALL TESTS PASSED");
        else
            $display("SOME TEST(S) FAILED");

        repeat(5) @(posedge clk);
        $finish;
    end

endmodule

waveforms/tb_pe.vcd
$date
   Sat Mar  7 15:08:13 2026
$end

$version
  2025.1.0
  $dumpfile ("tb_pe.vcd") 
$end

$timescale
  1ps
$end

$scope module tb_pe $end
$var reg 1 ! clk $end
$var reg 1 " rst_n $end
$var reg 8 # data_in [7:0] $end
$var reg 8 $ data_out [7:0] $end
$var reg 8 % weight_in [7:0] $end
$var reg 8 & weight_out [7:0] $end
$var reg 32 ' psum_in [31:0] $end
$var reg 32 ( psum_out [31:0] $end
$var reg 32 ) pass_count [31:0] $end
$var reg 32 * fail_count [31:0] $end
$scope module dut $end
$var wire 1 + i_clk $end
$var wire 1 , rst_n $end
$var wire 8 - i_data [7:0] $end
$var wire 8 . i_weight [7:0] $end
$var wire 32 / i_psum [31:0] $end
$var reg 8 $ o_data [7:0] $end
$var reg 8 & o_weight [7:0] $end
$var reg 32 ( o_psum [31:0] $end
$var reg 8 0 data_r [7:0] $end
$var reg 8 1 weight_r [7:0] $end
$var reg 32 2 psum_r [31:0] $end
$var reg 64 3 mult_r [63:0] $end
$var reg 32 4 mac_r [31:0] $end
$upscope $end
$scope begin Block95_4 $end
$var reg 32 5 i [31:0] $end
$upscope $end
$scope begin Block106_5 $end
$var reg 32 6 i [31:0] $end
$upscope $end
$scope task reset_dut $end
$upscope $end
$scope task test_mid_reset $end
$upscope $end
$upscope $end
$enddefinitions $end

#0
$dumpvars
0!
0"
b0 #
bx $
b0 %
bx &
b0 '
bx (
b0 )
b0 *
0+
0,
b0 -
b0 .
b0 /
bx 0
bx 1
bx 2
bx 3
bx 4
b1110000 5
b0 6
$end

#5000
1!
b0 $
b0 &
b0 (
1+
b0 0
b0 1
b0 2
b0 3
b0 4

#10000
0!
0+

#15000
1!
1"
1+
1,

#20000
0!
0+

#25000
1!
1+

#26000
b101 #
b11 %
b101 -
b11 .

#30000
0!
0+

#35000
1!
1+
b101 0
b11 1

#40000
0!
0+

#45000
1!
b101 $
b11 &
1+
b1111 3

#50000
0!
0+

#55000
1!
1+
b1111 4

#56000
b11111110 #
b100 %
b10 )
b11111110 -
b100 .
b1 6

#60000
0!
0+

#65000
1!
b1111 (
1+
b11111110 0
b100 1

#70000
0!
0+

#75000
1!
b11111110 $
b100 &
1+
b1111111111111111111111111111111111111111111111111111111111111000 3

#80000
0!
0+

#85000
1!
1+
b11111111111111111111111111111000 4

#86000
b101 #
b11 %
b1010 '
b100 )
b101 -
b11 .
b1010 /
b10 6

#90000
0!
0+

#95000
1!
b11111111111111111111111111111000 (
1+
b101 0
b11 1
b1010 2

#100000
0!
0+

#105000
1!
b101 $
b11 &
1+
b1111 3
b10 4

#110000
0!
0+

#115000
1!
b10 (
1+
b11001 4

#116000
b11111110 #
b1010 %
b11111111111111111111111111101100 '
b110 )
b11111110 -
b1010 .
b11111111111111111111111111101100 /
b11 6

#120000
0!
0+

#125000
1!
b11001 (
1+
b11111110 0
b1010 1
b11111111111111111111111111101100 2

#130000
0!
0+

#135000
1!
b11111110 $
b1010 &
1+
b1111111111111111111111111111111111111111111111111111111111101100 3
b11111111111111111111111111111011 4

#140000
0!
0+

#145000
1!
b11111111111111111111111111111011 (
1+
b11111111111111111111111111011000 4

#146000
b1111111 #
b1111111 %
b0 '
b1000 )
b1111111 -
b1111111 .
b0 /
b100 6

#150000
0!
0+

#155000
1!
b11111111111111111111111111011000 (
1+
b1111111 0
b1111111 1
b0 2

#160000
0!
0+

#165000
1!
b1111111 $
b1111111 &
1+
b11111100000001 3
b11111111111111111111111111101100 4

#170000
0!
0+

#175000
1!
b11111111111111111111111111101100 (
1+
b11111100000001 4

#176000
b10000000 #
b10000000 %
b1010 )
b10000000 -
b10000000 .
b101 6

#180000
0!
0+

#185000
1!
b11111100000001 (
1+
b10000000 0
b10000000 1

#190000
0!
0+

#195000
1!
b10000000 $
b10000000 &
1+
b100000000000000 3

#200000
0!
0+

#205000
1!
1+
b100000000000000 4

#206000
b0 #
b0 %
b1100 )
b0 -
b0 .
b110 6

#210000
0!
0+

#215000
1!
b100000000000000 (
1+
b0 0
b0 1

#220000
0!
0+

#225000
1!
b0 $
b0 &
1+
b0 3

#230000
0!
0+

#235000
1!
1+
b0 4

#236000
b1 #
b11111111 %
b1100100 '
b1110 )
b1 -
b11111111 .
b1100100 /
b111 6

#240000
0!
0+

#245000
1!
b0 (
1+
b1 0
b11111111 1
b1100100 2

#250000
0!
0+

#255000
1!
b1 $
b11111111 &
1+
b1111111111111111111111111111111111111111111111111111111111111111 3
b1100100 4

#260000
0!
0+

#265000
1!
b1100100 (
1+
b1100011 4

#266000
b1111111 #
b10000000 %
b0 '
b10000 )
b1111111 -
b10000000 .
b0 /
b1000 6

#270000
0!
0+

#275000
1!
b1100011 (
1+
b1111111 0
b10000000 1
b0 2

#280000
0!
0+

#285000
1!
b1111111 $
b10000000 &
1+
b1111111111111111111111111111111111111111111111111100000010000000 3
b11111111111111111111111111111111 4

#290000
0!
0+

#295000
1!
b11111111111111111111111111111111 (
1+
b11111111111111111100000010000000 4

#296000
b10000000 #
b1111111 %
b10010 )
b10000000 -
b1111111 .
b1001 6

#300000
0!
0+

#305000
1!
b11111111111111111100000010000000 (
1+
b10000000 0
b1111111 1

#310000
0!
0+

#315000
1!
b10000000 $
b1111111 &
1+

#320000
0!
0+

#325000
1!
1+

#326000
b1 #
b1 %
b111111111111111111111111111111 '
b10100 )
b1 -
b1 .
b111111111111111111111111111111 /
b1010 6

#330000
0!
0+

#335000
1!
1+
b1 0
b1 1
b111111111111111111111111111111 2

#340000
0!
0+

#345000
1!
b1 $
b1 &
1+
b1 3
b111111111111111100000001111111 4

#350000
0!
0+

#355000
1!
b111111111111111100000001111111 (
1+
b1000000000000000000000000000000 4

#356000
b11111111 #
b11000000000000000000000000000000 '
b10110 )
b11111111 -
b11000000000000000000000000000000 /
b1011 6

#360000
0!
0+

#365000
1!
b1000000000000000000000000000000 (
1+
b11111111 0
b11000000000000000000000000000000 2

#370000
0!
0+

#375000
1!
b11111111 $
1+
b1111111111111111111111111111111111111111111111111111111111111111 3
b11000000000000000000000000000001 4

#380000
0!
0+

#385000
1!
b11000000000000000000000000000001 (
1+
b10111111111111111111111111111111 4

#386000
b10111001 #
b10001100 %
b10111110101100010011101110010000 '
b11000 )
b10111001 -
b10001100 .
b10111110101100010011101110010000 /
b1100 6

#390000
0!
0+

#395000
1!
b10111111111111111111111111111111 (
1+
b10111001 0
b10001100 1
b10111110101100010011101110010000 2

#400000
0!
0+

#405000
1!
b10111001 $
b10001100 &
1+
b10000000101100 3
b10111110101100010011101110001111 4

#410000
0!
0+

#415000
1!
b10111110101100010011101110001111 (
1+
b10111110101100010101101110111100 4

#416000
b11000111 #
b10110100 %
b11101100000000110001000110011001 '
b11010 )
b11000111 -
b10110100 .
b11101100000000110001000110011001 /
b1101 6

#420000
0!
0+

#425000
1!
b10111110101100010101101110111100 (
1+
b11000111 0
b10110100 1
b11101100000000110001000110011001 2

#430000
0!
0+

#435000
1!
b11000111 $
b10110100 &
1+
b1000011101100 3
b11101100000000110011000111000101 4

#440000
0!
0+

#445000
1!
b11101100000000110011000111000101 (
1+
b11101100000000110010001010000101 4

#446000
b10001111 #
b10101111 %
b0 '
b11100 )
b10001111 -
b10101111 .
b0 /
b1110 6

#450000
0!
0+

#455000
1!
b11101100000000110010001010000101 (
1+
b10001111 0
b10101111 1
b0 2

#460000
0!
0+

#465000
1!
b10001111 $
b10101111 &
1+
b10001111000001 3
b1000011101100 4

#470000
0!
0+

#475000
1!
b1000011101100 (
1+
b10001111000001 4

#476000
b10001101 #
b11100101 %
b11101011011001011010011010100100 '
b11110 )
b10001101 -
b11100101 .
b11101011011001011010011010100100 /
b1111 6

#480000
0!
0+

#485000
1!
b10001111000001 (
1+
b10001101 0
b11100101 1
b11101011011001011010011010100100 2

#490000
0!
0+

#495000
1!
b10001101 $
b11100101 &
1+
b110000100001 3
b11101011011001011100101001100101 4

#500000
0!
0+

#505000
1!
b11101011011001011100101001100101 (
1+
b11101011011001011011001011000101 4

#506000
b1100101 #
b1110 %
b1001110010010100010101110111101 '
b100000 )
b1100101 -
b1110 .
b1001110010010100010101110111101 /
b10000 6

#510000
0!
0+

#515000
1!
b11101011011001011011001011000101 (
1+
b1100101 0
b1110 1
b1001110010010100010101110111101 2

#520000
0!
0+

#525000
1!
b1100101 $
b1110 &
1+
b10110000110 3
b1001110010010100011011111011110 4

#530000
0!
0+

#535000
1!
b1001110010010100011011111011110 (
1+
b1001110010010100011000101000011 4

#536000
bx #
bx %
bx '
b100010 )
bx -
bx .
bx /
b10001 6

#540000
0!
0+

#545000
1!
b1001110010010100011000101000011 (
1+
bx 0
bx 1
bx 2

#550000
0!
0+

#555000
1!
bx $
bx &
1+
bx 3
bx 4

#560000
0!
0+

#565000
1!
bx (
1+

#566000
b100100 )
b10010 6

#570000
0!
0+

#575000
1!
1+

#580000
0!
0+

#585000
1!
1+

#590000
0!
0+

#595000
1!
1+

#596000
b100110 )
b10011 6

#600000
0!
0+

#605000
1!
1+

#610000
0!
0+

#615000
1!
1+

#620000
0!
0+

#625000
1!
1+

#626000
b101000 )
b10100 6

#630000
0!
0+

#635000
1!
1+

#640000
0!
0+

#645000
1!
1+

#650000
0!
0+

#655000
1!
1+

#656000
b101010 )
b10101 6

#660000
0!
0+

#665000
1!
1+

#670000
0!
0+

#675000
1!
1+

#680000
0!
0+

#685000
1!
1+

#686000
b101100 )
b10110 6

#690000
0!
0+

#695000
1!
1+

#700000
0!
0+

#705000
1!
1+

#710000
0!
0+

#715000
1!
1+

#716000
b101110 )
b10111 6

#720000
0!
0+

#725000
1!
1+

#730000
0!
0+

#735000
1!
1+

#740000
0!
0+

#745000
1!
1+

#746000
b110000 )
b11000 6

#750000
0!
0+

#755000
1!
1+

#760000
0!
0+

#765000
1!
1+

#770000
0!
0+

#775000
1!
1+

#776000
b110010 )
b11001 6

#780000
0!
0+

#785000
1!
1+

#790000
0!
0+

#795000
1!
1+

#800000
0!
0+

#805000
1!
1+

#806000
b110100 )
b11010 6

#810000
0!
0+

#815000
1!
1+

#820000
0!
0+

#825000
1!
1+

#830000
0!
0+

#835000
1!
1+

#836000
b110110 )
b11011 6

#840000
0!
0+

#845000
1!
1+

#850000
0!
0+

#855000
1!
1+

#860000
0!
0+

#865000
1!
1+

#866000
b111000 )
b11100 6

#870000
0!
0+

#875000
1!
1+

#880000
0!
0+

#885000
1!
1+

#890000
0!
0+

#895000
1!
1+

#896000
b111010 )
b11101 6

#900000
0!
0+

#905000
1!
1+

#910000
0!
0+

#915000
1!
1+

#920000
0!
0+

#925000
1!
1+

#926000
b111100 )
b11110 6

#930000
0!
0+

#935000
1!
1+

#940000
0!
0+

#945000
1!
1+

#950000
0!
0+

#955000
1!
1+

#956000
b111110 )
b11111 6

#960000
0!
0+

#965000
1!
1+

#970000
0!
0+

#975000
1!
1+

#980000
0!
0+

#985000
1!
1+

#986000
b1000000 )
b100000 6

#990000
0!
0+

#995000
1!
1+

#1000000
0!
0+

#1005000
1!
1+

#1010000
0!
0+

#1015000
1!
1+

#1016000
b1000010 )
b100001 6

#1020000
0!
0+

#1025000
1!
1+

#1030000
0!
0+

#1035000
1!
1+

#1040000
0!
0+

#1045000
1!
1+

#1046000
b1000100 )
b100010 6

#1050000
0!
0+

#1055000
1!
1+

#1060000
0!
0+

#1065000
1!
1+

#1070000
0!
0+

#1075000
1!
1+

#1076000
b1000110 )
b100011 6

#1080000
0!
0+

#1085000
1!
1+

#1090000
0!
0+

#1095000
1!
1+

#1100000
0!
0+

#1105000
1!
1+

#1106000
b1001000 )
b100100 6

#1110000
0!
0+

#1115000
1!
1+

#1120000
0!
0+

#1125000
1!
1+

#1130000
0!
0+

#1135000
1!
1+

#1136000
b1001010 )
b100101 6

#1140000
0!
0+

#1145000
1!
1+

#1150000
0!
0+

#1155000
1!
1+

#1160000
0!
0+

#1165000
1!
1+

#1166000
b1001100 )
b100110 6

#1170000
0!
0+

#1175000
1!
1+

#1180000
0!
0+

#1185000
1!
1+

#1190000
0!
0+

#1195000
1!
1+

#1196000
b1001110 )
b100111 6

#1200000
0!
0+

#1205000
1!
1+

#1210000
0!
0+

#1215000
1!
1+

#1220000
0!
0+

#1225000
1!
1+

#1226000
b1010000 )
b101000 6

#1230000
0!
0+

#1235000
1!
1+

#1240000
0!
0+

#1245000
1!
1+

#1250000
0!
0+

#1255000
1!
1+

#1256000
b1010010 )
b101001 6

#1260000
0!
0+

#1265000
1!
1+

#1270000
0!
0+

#1275000
1!
1+

#1280000
0!
0+

#1285000
1!
1+

#1286000
b1010100 )
b101010 6

#1290000
0!
0+

#1295000
1!
1+

#1300000
0!
0+

#1305000
1!
1+

#1310000
0!
0+

#1315000
1!
1+

#1316000
b1010110 )
b101011 6

#1320000
0!
0+

#1325000
1!
1+

#1330000
0!
0+

#1335000
1!
1+

#1340000
0!
0+

#1345000
1!
1+

#1346000
b1011000 )
b101100 6

#1350000
0!
0+

#1355000
1!
1+

#1360000
0!
0+

#1365000
1!
1+

#1370000
0!
0+

#1375000
1!
1+

#1376000
b1011010 )
b101101 6

#1380000
0!
0+

#1385000
1!
1+

#1390000
0!
0+

#1395000
1!
1+

#1400000
0!
0+

#1405000
1!
1+

#1406000
b1011100 )
b101110 6

#1410000
0!
0+

#1415000
1!
1+

#1420000
0!
0+

#1425000
1!
1+

#1430000
0!
0+

#1435000
1!
1+

#1436000
b1011110 )
b101111 6

#1440000
0!
0+

#1445000
1!
1+

#1450000
0!
0+

#1455000
1!
1+

#1460000
0!
0+

#1465000
1!
1+

#1466000
b1100000 )
b110000 6

#1470000
0!
0+

#1475000
1!
1+

#1480000
0!
0+

#1485000
1!
1+

#1490000
0!
0+

#1495000
1!
1+

#1496000
b1100010 )
b110001 6

#1500000
0!
0+

#1505000
1!
1+

#1510000
0!
0+

#1515000
1!
1+

#1520000
0!
0+

#1525000
1!
1+

#1526000
b1100100 )
b110010 6

#1530000
0!
0+

#1535000
1!
1+

#1540000
0!
0+

#1545000
1!
1+

#1550000
0!
0+

#1555000
1!
1+

#1556000
b1100110 )
b110011 6

#1560000
0!
0+

#1565000
1!
1+

#1570000
0!
0+

#1575000
1!
1+

#1580000
0!
0+

#1585000
1!
1+

#1586000
b1101000 )
b110100 6

#1590000
0!
0+

#1595000
1!
1+

#1600000
0!
0+

#1605000
1!
1+

#1610000
0!
0+

#1615000
1!
1+

#1616000
b1101010 )
b110101 6

#1620000
0!
0+

#1625000
1!
1+

#1630000
0!
0+

#1635000
1!
1+

#1640000
0!
0+

#1645000
1!
1+

#1646000
b1101100 )
b110110 6

#1650000
0!
0+

#1655000
1!
1+

#1660000
0!
0+

#1665000
1!
1+

#1670000
0!
0+

#1675000
1!
1+

#1676000
b1101110 )
b110111 6

#1680000
0!
0+

#1685000
1!
1+

#1690000
0!
0+

#1695000
1!
1+

#1700000
0!
0+

#1705000
1!
1+

#1706000
b1110000 )
b111000 6

#1710000
0!
0+

#1715000
1!
1+

#1720000
0!
0+

#1725000
1!
1+

#1730000
0!
0+

#1735000
1!
1+

#1736000
b1110010 )
b111001 6

#1740000
0!
0+

#1745000
1!
1+

#1750000
0!
0+

#1755000
1!
1+

#1760000
0!
0+

#1765000
1!
1+

#1766000
b1110100 )
b111010 6

#1770000
0!
0+

#1775000
1!
1+

#1780000
0!
0+

#1785000
1!
1+

#1790000
0!
0+

#1795000
1!
1+

#1796000
b1110110 )
b111011 6

#1800000
0!
0+

#1805000
1!
1+

#1810000
0!
0+

#1815000
1!
1+

#1820000
0!
0+

#1825000
1!
1+

#1826000
b1111000 )
b111100 6

#1830000
0!
0+

#1835000
1!
1+

#1840000
0!
0+

#1845000
1!
1+

#1850000
0!
0+

#1855000
1!
1+

#1856000
b1111010 )
b111101 6

#1860000
0!
0+

#1865000
1!
1+

#1870000
0!
0+

#1875000
1!
1+

#1880000
0!
0+

#1885000
1!
1+

#1886000
b1111100 )
b111110 6

#1890000
0!
0+

#1895000
1!
1+

#1900000
0!
0+

#1905000
1!
1+

#1910000
0!
0+

#1915000
1!
1+

#1916000
b1111110 )
b111111 6

#1920000
0!
0+

#1925000
1!
1+

#1930000
0!
0+

#1935000
1!
1+

#1940000
0!
0+

#1945000
1!
1+

#1946000
b10000000 )
b1000000 6

#1950000
0!
0+

#1955000
1!
1+

#1960000
0!
0+

#1965000
1!
1+

#1970000
0!
0+

#1975000
1!
1+

#1976000
b10000010 )
b1000001 6

#1980000
0!
0+

#1985000
1!
1+

#1990000
0!
0+

#1995000
1!
1+

#2000000
0!
0+

#2005000
1!
1+

#2006000
b10000100 )
b1000010 6

#2010000
0!
0+

#2015000
1!
1+

#2020000
0!
0+

#2025000
1!
1+

#2030000
0!
0+

#2035000
1!
1+

#2036000
b10000110 )
b1000011 6

#2040000
0!
0+

#2045000
1!
1+

#2050000
0!
0+

#2055000
1!
1+

#2060000
0!
0+

#2065000
1!
1+

#2066000
b10001000 )
b1000100 6

#2070000
0!
0+

#2075000
1!
1+

#2080000
0!
0+

#2085000
1!
1+

#2090000
0!
0+

#2095000
1!
1+

#2096000
b10001010 )
b1000101 6

#2100000
0!
0+

#2105000
1!
1+

#2110000
0!
0+

#2115000
1!
1+

#2120000
0!
0+

#2125000
1!
1+

#2126000
b10001100 )
b1000110 6

#2130000
0!
0+

#2135000
1!
1+

#2140000
0!
0+

#2145000
1!
1+

#2150000
0!
0+

#2155000
1!
1+

#2156000
b10001110 )
b1000111 6

#2160000
0!
0+

#2165000
1!
1+

#2170000
0!
0+

#2175000
1!
1+

#2180000
0!
0+

#2185000
1!
1+

#2186000
b10010000 )
b1001000 6

#2190000
0!
0+

#2195000
1!
1+

#2200000
0!
0+

#2205000
1!
1+

#2210000
0!
0+

#2215000
1!
1+

#2216000
b10010010 )
b1001001 6

#2220000
0!
0+

#2225000
1!
1+

#2230000
0!
0+

#2235000
1!
1+

#2240000
0!
0+

#2245000
1!
1+

#2246000
b10010100 )
b1001010 6

#2250000
0!
0+

#2255000
1!
1+

#2260000
0!
0+

#2265000
1!
1+

#2270000
0!
0+

#2275000
1!
1+

#2276000
b10010110 )
b1001011 6

#2280000
0!
0+

#2285000
1!
1+

#2290000
0!
0+

#2295000
1!
1+

#2300000
0!
0+

#2305000
1!
1+

#2306000
b10011000 )
b1001100 6

#2310000
0!
0+

#2315000
1!
1+

#2320000
0!
0+

#2325000
1!
1+

#2330000
0!
0+

#2335000
1!
1+

#2336000
b10011010 )
b1001101 6

#2340000
0!
0+

#2345000
1!
1+

#2350000
0!
0+

#2355000
1!
1+

#2360000
0!
0+

#2365000
1!
1+

#2366000
b10011100 )
b1001110 6

#2370000
0!
0+

#2375000
1!
1+

#2380000
0!
0+

#2385000
1!
1+

#2390000
0!
0+

#2395000
1!
1+

#2396000
b10011110 )
b1001111 6

#2400000
0!
0+

#2405000
1!
1+

#2410000
0!
0+

#2415000
1!
1+

#2420000
0!
0+

#2425000
1!
1+

#2426000
b10100000 )
b1010000 6

#2430000
0!
0+

#2435000
1!
1+

#2440000
0!
0+

#2445000
1!
1+

#2450000
0!
0+

#2455000
1!
1+

#2456000
b10100010 )
b1010001 6

#2460000
0!
0+

#2465000
1!
1+

#2470000
0!
0+

#2475000
1!
1+

#2480000
0!
0+

#2485000
1!
1+

#2486000
b10100100 )
b1010010 6

#2490000
0!
0+

#2495000
1!
1+

#2500000
0!
0+

#2505000
1!
1+

#2510000
0!
0+

#2515000
1!
1+

#2516000
b10100110 )
b1010011 6

#2520000
0!
0+

#2525000
1!
1+

#2530000
0!
0+

#2535000
1!
1+

#2540000
0!
0+

#2545000
1!
1+

#2546000
b10101000 )
b1010100 6

#2550000
0!
0+

#2555000
1!
1+

#2560000
0!
0+

#2565000
1!
1+

#2570000
0!
0+

#2575000
1!
1+

#2576000
b10101010 )
b1010101 6

#2580000
0!
0+

#2585000
1!
1+

#2590000
0!
0+

#2595000
1!
1+

#2600000
0!
0+

#2605000
1!
1+

#2606000
b10101100 )
b1010110 6

#2610000
0!
0+

#2615000
1!
1+

#2620000
0!
0+

#2625000
1!
1+

#2630000
0!
0+

#2635000
1!
1+

#2636000
b10101110 )
b1010111 6

#2640000
0!
0+

#2645000
1!
1+

#2650000
0!
0+

#2655000
1!
1+

#2660000
0!
0+

#2665000
1!
1+

#2666000
b10110000 )
b1011000 6

#2670000
0!
0+

#2675000
1!
1+

#2680000
0!
0+

#2685000
1!
1+

#2690000
0!
0+

#2695000
1!
1+

#2696000
b10110010 )
b1011001 6

#2700000
0!
0+

#2705000
1!
1+

#2710000
0!
0+

#2715000
1!
1+

#2720000
0!
0+

#2725000
1!
1+

#2726000
b10110100 )
b1011010 6

#2730000
0!
0+

#2735000
1!
1+

#2740000
0!
0+

#2745000
1!
1+

#2750000
0!
0+

#2755000
1!
1+

#2756000
b10110110 )
b1011011 6

#2760000
0!
0+

#2765000
1!
1+

#2770000
0!
0+

#2775000
1!
1+

#2780000
0!
0+

#2785000
1!
1+

#2786000
b10111000 )
b1011100 6

#2790000
0!
0+

#2795000
1!
1+

#2800000
0!
0+

#2805000
1!
1+

#2810000
0!
0+

#2815000
1!
1+

#2816000
b10111010 )
b1011101 6

#2820000
0!
0+

#2825000
1!
1+

#2830000
0!
0+

#2835000
1!
1+

#2840000
0!
0+

#2845000
1!
1+

#2846000
b10111100 )
b1011110 6

#2850000
0!
0+

#2855000
1!
1+

#2860000
0!
0+

#2865000
1!
1+

#2870000
0!
0+

#2875000
1!
1+

#2876000
b10111110 )
b1011111 6

#2880000
0!
0+

#2885000
1!
1+

#2890000
0!
0+

#2895000
1!
1+

#2900000
0!
0+

#2905000
1!
1+

#2906000
b11000000 )
b1100000 6

#2910000
0!
0+

#2915000
1!
1+

#2920000
0!
0+

#2925000
1!
1+

#2930000
0!
0+

#2935000
1!
1+

#2936000
b11000010 )
b1100001 6

#2940000
0!
0+

#2945000
1!
1+

#2950000
0!
0+

#2955000
1!
1+

#2960000
0!
0+

#2965000
1!
1+

#2966000
b11000100 )
b1100010 6

#2970000
0!
0+

#2975000
1!
1+

#2980000
0!
0+

#2985000
1!
1+

#2990000
0!
0+

#2995000
1!
1+

#2996000
b11000110 )
b1100011 6

#3000000
0!
0+

#3005000
1!
1+

#3010000
0!
0+

#3015000
1!
1+

#3020000
0!
0+

#3025000
1!
1+

#3026000
b11001000 )
b1100100 6

#3030000
0!
0+

#3035000
1!
1+

#3040000
0!
0+

#3045000
1!
1+

#3050000
0!
0+

#3055000
1!
1+

#3056000
b11001010 )
b1100101 6

#3060000
0!
0+

#3065000
1!
1+

#3070000
0!
0+

#3075000
1!
1+

#3080000
0!
0+

#3085000
1!
1+

#3086000
b11001100 )
b1100110 6

#3090000
0!
0+

#3095000
1!
1+

#3100000
0!
0+

#3105000
1!
1+

#3110000
0!
0+

#3115000
1!
1+

#3116000
b11001110 )
b1100111 6

#3120000
0!
0+

#3125000
1!
1+

#3130000
0!
0+

#3135000
1!
1+

#3140000
0!
0+

#3145000
1!
1+

#3146000
b11010000 )
b1101000 6

#3150000
0!
0+

#3155000
1!
1+

#3160000
0!
0+

#3165000
1!
1+

#3170000
0!
0+

#3175000
1!
1+

#3176000
b11010010 )
b1101001 6

#3180000
0!
0+

#3185000
1!
1+

#3190000
0!
0+

#3195000
1!
1+

#3200000
0!
0+

#3205000
1!
1+

#3206000
b11010100 )
b1101010 6

#3210000
0!
0+

#3215000
1!
1+

#3220000
0!
0+

#3225000
1!
1+

#3230000
0!
0+

#3235000
1!
1+

#3236000
b11010110 )
b1101011 6

#3240000
0!
0+

